moch/__init__.py
moch/cli.py
moch/highlighters/__init__.py
moch/highlighters/pattern_highlight.py
moch/logic/Debouncer.py
moch/logic/GlobalState.py
moch/logic/RegexLogic.py
moch/logic/__init__.py
moch/metaclasses/__init__.py
moch/metaclasses/singelton.py
moch/moch.py
moch/screens/Help/Help.py
moch/screens/Help/HelpScreen.tcss
moch/screens/Help/__init__.py
moch/screens/Home/Home.py
moch/screens/Home/Home.tcss
moch/screens/Home/__init__.py
moch/screens/RegexModes/RegexModes.py
moch/screens/RegexModes/RegexModes.tcss
moch/screens/RegexModes/__init__.py
moch/screens/RegexOptions/RegexOptions.py
moch/screens/RegexOptions/RegexOptions.tcss
moch/screens/RegexOptions/__init__.py
moch/screens/__init__.py
moch/widgets/__init__.py
moch/widgets/inputs/CmdInput/CmdInput.py
moch/widgets/inputs/CmdInput/__init__.py
moch/widgets/inputs/ColoredInputArea/ColoredInputArea.py
moch/widgets/inputs/ColoredInputArea/__init__.py
moch/widgets/inputs/PatternInput/PatternInput.py
moch/widgets/inputs/PatternInput/__init__.py
moch/widgets/inputs/SubstitutionInput/SubstitutionInput.py
moch/widgets/inputs/SubstitutionInput/__init__.py
moch/widgets/inputs/SubstitutionInputArea/SubstitutionInputArea.py
moch/widgets/inputs/SubstitutionInputArea/__init__.py
moch/widgets/inputs/__init__.py
moch/widgets/labels/Logo/Logo.py
moch/widgets/labels/Logo/__init__.py
moch/widgets/labels/__init__.py
moch/widgets/widgets/CustomHeader/CustomHeader.py
moch/widgets/widgets/CustomHeader/__init__.py
moch/widgets/widgets/FooterMode/FooterMode.py
moch/widgets/widgets/FooterMode/__init__.py
moch/widgets/widgets/FooterOptions/FooterOptions.py
moch/widgets/widgets/FooterOptions/__init__.py
moch/widgets/widgets/GeneralData/GeneralData.py
moch/widgets/widgets/GeneralData/__init__.py
moch/widgets/widgets/GroupsArea/GroupsArea.py
moch/widgets/widgets/GroupsArea/__init__.py
moch/widgets/widgets/Help/Help.py
moch/widgets/widgets/Help/__init__.py
moch/widgets/widgets/HelpData/HelpData.py
moch/widgets/widgets/HelpData/__init__.py
moch-0.2.7.dist-info/LICENSE
moch-0.2.7.dist-info/METADATA
moch-0.2.7.dist-info/WHEEL
moch-0.2.7.dist-info/entry_points.txt
moch-0.2.7.dist-info/RECORD
